YaTrackerApi/__init__.py
YaTrackerApi/base.py
YaTrackerApi/entities/__init__.py
YaTrackerApi/entities/api.py
YaTrackerApi/entities/bulk.py
YaTrackerApi/entities/checklist_item.py
YaTrackerApi/entities/checklists.py
YaTrackerApi/entities/links.py
YaTrackerApi/fields/__init__.py
YaTrackerApi/fields/api.py
YaTrackerApi/fields/local.py
YaTrackerApi/issues/__init__.py
YaTrackerApi/issues/api.py
YaTrackerApi/issues/checklist_item.py
YaTrackerApi/issues/checklists.py
YaTrackerApi/issues/comments.py
YaTrackerApi/issues/links.py
YaTrackerApi/issues/transitions.py
YaTrackerApi/queues/__init__.py
YaTrackerApi/queues/api.py
YaTrackerApi/queues/bulk.py
YaTrackerApi/queues/fields.py
YaTrackerApi/queues/group.py
YaTrackerApi/queues/tags.py
YaTrackerApi/queues/user.py
YaTrackerApi/queues/versions.py
YaTrackerApi/users/__init__.py
YaTrackerApi/users/api.py
yatrackerapi-2.1.3.dist-info/METADATA
yatrackerapi-2.1.3.dist-info/WHEEL
yatrackerapi-2.1.3.dist-info/licenses/LICENSE
yatrackerapi-2.1.3.dist-info/RECORD
