Metadata-Version: 2.4
Name: YaTrackerApi
Version: 2.1.3
Summary: Асинхронный Python клиент для работы с Yandex Tracker API с модульной архитектурой
Project-URL: Homepage, https://github.com/imdeniil/YaTrackerApi
Project-URL: Repository, https://github.com/imdeniil/YaTrackerApi
Project-URL: Issues, https://github.com/imdeniil/YaTrackerApi/issues
Project-URL: Documentation, https://github.com/imdeniil/YaTrackerApi#readme
Author-email: Даниил <keemor821@gmail.com>
Maintainer-email: Даниил <keemor821@gmail.com>
License: MIT
License-File: LICENSE
Keywords: aiohttp,api,async,project-management,task-tracker,tracker,yandex
Classifier: Development Status :: 4 - Beta
Classifier: Framework :: AsyncIO
Classifier: Intended Audience :: Developers
Classifier: License :: OSI Approved :: MIT License
Classifier: Operating System :: OS Independent
Classifier: Programming Language :: Python :: 3
Classifier: Programming Language :: Python :: 3.9
Classifier: Programming Language :: Python :: 3.10
Classifier: Programming Language :: Python :: 3.11
Classifier: Programming Language :: Python :: 3.12
Classifier: Programming Language :: Python :: 3.13
Classifier: Topic :: Office/Business :: Groupware
Classifier: Topic :: Software Development :: Libraries :: Python Modules
Requires-Python: >=3.9
Requires-Dist: aiohttp>=3.12.15
Requires-Dist: python-dotenv>=1.1.1
